MANIFEST.in
README.md
requirements.txt
setup.py
data/fig/Lena.png
data/fig/SAR&ellipse1024.png
data/fig/SAR&ellipse256.png
data/fig/SAR128.png
data/fig/SAR512.png
data/fig/SAR64.png
data/fig/SARDL.png
data/fig/circle1024.png
data/fig/ellipse1024.png
data/fig/ellipse256.png
data/fig/ellipse512.png
data/fig/gaoxiong001.png
data/fig/iridescent.png
data/fig/line1024.png
data/fig/line256.png
data/fig/randcircle.png
data/fig/strip1024.png
data/fig/stripslim1024.png
data/fig/zhi&yan.png
data/img/000002AirPlane128.png
data/img/000002AirPlane32.png
data/img/000002AirPlane64.png
data/img/000003Ground128.png
data/img/000003Ground32.png
data/img/000003Ground64.png
data/img/000004Ground128.png
data/img/000004Ground32.png
data/img/000004Ground64.png
data/img/000010.png
data/img/000043.png
data/img/000055AirPlane128.png
data/img/000055AirPlane32.png
data/img/000055AirPlane64.png
data/img/000066.png
data/img/000237.png
data/img/Lighthouse.png
data/img/Lotus128.png
data/img/Lotus256.png
data/img/Lotus32.png
data/img/Lotus512.png
data/img/Lotus64.png
data/img/points128.png
data/img/points32.png
data/img/points64.png
data/img/pointsx128.png
data/img/pointsx32.png
data/img/pointsx64.png
data/img/ship128.png
data/img/ship256.png
data/img/ship32.png
data/img/ship64.png
examples/__init__.py
examples/demo_CS.py
examples/demo_noise.py
iprs/__init__.py
iprs.egg-info/PKG-INFO
iprs.egg-info/SOURCES.txt
iprs.egg-info/dependency_links.txt
iprs.egg-info/requires.txt
iprs.egg-info/top_level.txt
iprs/autofocus/__init__.py
iprs/autofocus/map_drift.py
iprs/autofocus/minimum_entropy.py
iprs/autofocus/phase_gradient.py
iprs/autofocus/regularization.py
iprs/calibration/__init__.py
iprs/calibration/multilook_process.py
iprs/calibration/radar_cross_section.py
iprs/calibration/sar_preprocess.py
iprs/dsp/__init__.py
iprs/dsp/convolution.py
iprs/dsp/correlation.py
iprs/dsp/fft.py
iprs/dsp/interpolation.py
iprs/dsp/noise.py
iprs/dsp/normalsignals.py
iprs/evaluation/__init__.py
iprs/evaluation/ent.py
iprs/evaluation/error.py
iprs/evaluation/mlw.py
iprs/evaluation/snr.py
iprs/evaluation/tbed.py
iprs/evaluation/tbr.py
iprs/imaging/__init__.py
