Metadata-Version: 2.1
Name: iprs
Version: 1.0.4
Summary: Intelligent Processing for Radar Signals
Home-page: http://iridescent.ink/iprs3.0
Author: Zhi Liu
Author-email: zhiliu.mind@gmail.com
License: UNKNOWN
Download-URL: https://github.com/antsfamily/iprs
Platform: UNKNOWN
Classifier: Programming Language :: Python :: 3
Classifier: Operating System :: OS Independent
